jinja-terraform-output/__init__.py
jinja_terraform_output/__init__.py
jinja_tfcloud_output/__init__.py
jinja_tfcloud_output-2.0.2.dist-info/METADATA
jinja_tfcloud_output-2.0.2.dist-info/WHEEL
jinja_tfcloud_output-2.0.2.dist-info/top_level.txt
jinja_tfcloud_output-2.0.2.dist-info/RECORD
