Metadata-Version: 2.1
Name: jinja-tfcloud-output
Version: 2.0.2
Summary: A Jinja extension to fetch terraform state output versions
Author: lummo-io
Author-email: dev@lummo.com
License: MIT
Requires-Dist: Jinja2 (<4)
Requires-Dist: requests (<3)
